tabular_time_series/__init__.py
tabular_time_series/tsdf.py
tabular_time_series/tsgenerator.py
tabular_time_series/tsgeneratoronline.py
tabular_time_series-1.1.3.dist-info/LICENSE
tabular_time_series-1.1.3.dist-info/WHEEL
tabular_time_series-1.1.3.dist-info/METADATA
tabular_time_series-1.1.3.dist-info/RECORD
