Metadata-Version: 2.1
Name: tabular-time-series
Version: 1.1.3
Summary: 
Home-page: https://github.com/felipewhitaker/tabular-time-series
License: MIT
Author: Felipe Whitaker
Author-email: felipewhitaker@gmail.com
Requires-Python: >=3.8,<3.11
Classifier: License :: OSI Approved :: MIT License
Classifier: Programming Language :: Python :: 3
Classifier: Programming Language :: Python :: 3.8
Classifier: Programming Language :: Python :: 3.9
Requires-Dist: pandas (>=1.3.2,<2.0.0)
Requires-Dist: pre-commit (>=2.15.0,<3.0.0)
Project-URL: Repository, https://github.com/felipewhitaker/tabular-time-series
